envgen/__init__.py
envgen/envgen.py
envgen/interface.py
envgen/server.py
envgen-0.0.3.dist-info/METADATA
envgen-0.0.3.dist-info/RECORD
envgen-0.0.3.dist-info/WHEEL
envgen-0.0.3.dist-info/entry_points.txt
envgen-0.0.3.dist-info/top_level.txt
