Metadata-Version: 2.1
Name: envgen
Version: 0.0.3
Summary: A Virtual Environment Generator
Home-page: https://github.com/jonebeabout/envgen
Author: Jonathan Beabout
Author-email: jonebeabout@gmail.com
License: UNKNOWN
Platform: UNKNOWN
Classifier: Programming Language :: Python :: 2
Classifier: License :: OSI Approved :: MIT License
Classifier: Operating System :: Microsoft :: Windows :: Windows 10
Requires-Dist: aniso8601 (>=3.0.2)
Requires-Dist: asn1crypto (>=0.24.0)
Requires-Dist: bcrypt (>=3.1.4)
Requires-Dist: cffi (>=1.11.5)
Requires-Dist: click (>=6.7)
Requires-Dist: colorama (>=0.3.9)
Requires-Dist: cryptography (>=2.2.2)
Requires-Dist: enum34 (>=1.1.6)
Requires-Dist: fabric (>=2.2.0)
Requires-Dist: Flask (>=1.0.2)
Requires-Dist: Flask-RESTful (>=0.3.6)
Requires-Dist: idna (>=2.7)
Requires-Dist: invoke (>=1.1.0)
Requires-Dist: ipaddress (>=1.0.22)
Requires-Dist: itsdangerous (>=0.24)
Requires-Dist: Jinja2 (>=2.10)
Requires-Dist: MarkupSafe (>=1.0)
Requires-Dist: paramiko (>=2.4.1)
Requires-Dist: psutil (>=5.4.6)
Requires-Dist: pyasn1 (>=0.4.3)
Requires-Dist: pycparser (>=2.18)
Requires-Dist: PyNaCl (>=1.2.1)
Requires-Dist: python-vagrant (>=0.5.15)
Requires-Dist: pytz (>=2018.5)
Requires-Dist: six (>=1.11.0)
Requires-Dist: Werkzeug (>=0.14.1)
